{
    "2022-07-01 00:00:00.0": {
        "PC0081": 733,
        "PC0085": 371,
        "PC0045": 888
    },
    "2022-07-02 00:00:00.0": {
        "PC0085": 183,
        "PC0049": 53,
        "PC0045": 932,
        "PC0073": 813
    },
    "2022-07-03 00:00:00.0": {
        "PC0077": 149,
        "PC0045": 820,
        "PC0049": 803,
        "PC0073": 839
    },
    "2022-07-04 00:00:00.0": {
        "PC0049": 120,
        "PC0084": 556,
        "PC0077": 101,
        "PC0073": 851
    },
    "2022-07-05 00:00:00.0": {
        "PC0081": 465,
        "PC0084": 922
    },
    "2022-07-06 00:00:00.0": {
        "PC0084": 929,
        "PC0049": 237,
        "PC0081": 864
    },
    "2022-07-07 00:00:00.0": {
        "PC0067": 625,
        "PC0049": 109,
        "PC0081": 749,
        "PC0084": 349
    },
    "2022-07-08 00:00:00.0": {
        "PC0067": 721,
        "PC0081": 868
    },
    "2022-07-09 00:00:00.0": {
        "PC0067": 537,
        "PC0081": 933
    },
    "2022-07-10 00:00:00.0": {
        "PC0039": 254,
        "PC0067": 797,
        "PC0081": 888
    },
    "2022-07-11 00:00:00.0": {
        "PC0084": 715,
        "PC0067": 519,
        "PC0039": 393,
        "PC0081": 951
    },
    "2022-07-12 00:00:00.0": {
        "PC0067": 633,
        "PC0081": 960,
        "PC0084": 249
    },
    "2022-07-13 00:00:00.0": {
        "PC0067": 686,
        "PC0084": 841,
        "PC0081": 536
    },
    "2022-07-14 00:00:00.0": {
        "PC0081": 910,
        "PC0084": 428,
        "PC0067": 467
    },
    "2022-07-15 00:00:00.0": {
        "PC0084": 930,
        "PC0081": 801,
        "PC0067": 1015
    },
    "2022-07-16 00:00:00.0": {
        "PC0067": 1089,
        "PC0084": 932,
        "PC0081": 859
    },
    "2022-07-17 00:00:00.0": {
        "PC0081": 199,
        "PC0067": 862,
        "PC0084": 921,
        "PC0073": 328
    },
    "2022-07-18 00:00:00.0": {
        "PC0084": 1024,
        "PC0067": 1068,
        "PC0073": 738
    },
    "2022-07-19 00:00:00.0": {
        "PC0073": 404,
        "PC0084": 342,
        "PC0076": 524,
        "PC0067": 452
    },
    "2022-07-20 00:00:00.0": {
        "PC0075": 1085,
        "PC0073": 1025,
        "PC0084": 458
    },
    "2022-07-21 00:00:00.0": {
        "PC0084": 900,
        "PC0073": 900,
        "PC0085": 881
    },
    "2022-07-22 00:00:00.0": {
        "PC0085": 500,
        "PC0073": 900,
        "PC0033": 900
    },
    "2022-07-23 00:00:00.0": {
        "PC0067": 779,
        "PC0033": 1150
    },
    "2022-07-24 00:00:00.0": {
        "PC0073": 900,
        "PC0067": 500,
        "PC0033": 179,
        "PC0086": 900
    },
    "2022-07-25 00:00:00.0": {
        "PC0086": 450,
        "PC0073": 900,
        "PC0084": 900
    },
    "2022-07-26 00:00:00.0": {
        "PC0084": 790,
        "PC0081": 900,
        "PC0067": 900
    },
    "2022-07-27 00:00:00.0": {
        "PC0067": 900,
        "PC0081": 889
    },
    "2022-07-28 00:00:00.0": {
        "PC0084": 400,
        "PC0033": 450,
        "PC0067": 900,
        "PC0068": 900
    },
    "2022-07-29 00:00:00.0": {
        "PC0068": 900,
        "PC0067": 900,
        "PC0084": 900
    },
    "2022-07-30 00:00:00.0": {
        "PC0067": 474,
        "PC0084": 900,
        "PC0033": 900
    },
    "2022-07-31 00:00:00.0": {
        "PC0084": 900,
        "PC0073": 895
    }
}