{
    "2022-09-01 00:00:00.0": {
        "PC0073": 658,
        "PC0086": 143
    },
    "2022-09-02 00:00:00.0": {
        "PC0028": 10,
        "PC0086": 37,
        "PC0073": 531
    },
    "2022-09-03 00:00:00.0": {
        "PC0084": 587,
        "PC0065": 397,
        "PC0073": 399
    },
    "2022-09-04 00:00:00.0": {
        "PC0065": 594,
        "PC0084": 1033,
        "PC0073": 579
    },
    "2022-09-05 00:00:00.0": {
        "PC0065": 641,
        "PC0084": 865,
        "PC0073": 72,
        "PC0085": 157
    },
    "2022-09-06 00:00:00.0": {
        "PC0085": 137,
        "PC0084": 917,
        "PC0073": 1
    },
    "2022-09-07 00:00:00.0": {
        "PC0067": 207,
        "PC0073": 730,
        "PC0084": 882,
        "PC0085": 252
    },
    "2022-09-08 00:00:00.0": {
        "PC0067": 662,
        "PC0084": 146,
        "PC0073": 693
    },
    "2022-09-09 00:00:00.0": {
        "PC0067": 784,
        "PC0084": 758,
        "PC0079": 154,
        "PC0073": 552
    },
    "2022-09-10 00:00:00.0": {
        "PC0079": 52,
        "PC0067": 823,
        "PC0084": 879,
        "PC0086": 46
    },
    "2022-09-11 00:00:00.0": {
        "PC0086": 217,
        "PC0084": 936,
        "PC0081": 165,
        "PC0067": 842
    },
    "2022-09-12 00:00:00.0": {
        "PC0086": 520,
        "PC0084": 747,
        "PC0081": 779,
        "PC0067": 840
    },
    "2022-09-13 00:00:00.0": {
        "PC0084": 294,
        "PC0067": 1032,
        "PC0086": 218,
        "PC0081": 919
    },
    "2022-09-14 00:00:00.0": {
        "PC0067": 348,
        "PC0084": 642,
        "PC0049": 19,
        "PC0081": 773
    },
    "2022-09-15 00:00:00.0": {
        "PC0049": 780,
        "PC0081": 731
    },
    "2022-09-16 00:00:00.0": {
        "PC0081": 926,
        "PC0049": 908
    },
    "2022-09-17 00:00:00.0": {
        "PC0081": 610,
        "PC0049": 105
    },
    "2022-09-18 00:00:00.0": {
        "PC0065": 437,
        "PC0049": 50,
        "PC0081": 653,
        "PC0039": 110
    },
    "2022-09-19 00:00:00.0": {
        "PC0039": 616,
        "PC0081": 728,
        "PC0065": 1552
    },
    "2022-09-20 00:00:00.0": {
        "PC0085": 416,
        "PC0086": 428
    },
    "2022-09-21 00:00:00.0": {
        "PC0086": 138,
        "PC0081": 303,
        "PC0085": 870
    },
    "2022-09-22 00:00:00.0": {
        "PC0028": 995,
        "PC0076": 500,
        "PC0081": 995,
        "PC0085": 2
    },
    "2022-09-23 00:00:00.0": {
        "PC0028": 495,
        "PC0068": 388,
        "PC0076": 400,
        "PC0081": 1000
    },
    "2022-09-24 00:00:00.0": {
        "PC0086": 435,
        "PC0068": 900
    },
    "2022-09-25 00:00:00.0": {
        "PC0086": 900,
        "PC0081": 995,
        "PC0069": 160
    },
    "2022-09-26 00:00:00.0": {
        "PC0067": 804,
        "PC0081": 1000,
        "PC0086": 101,
        "PC0084": 771
    },
    "2022-09-27 00:00:00.0": {
        "PC0084": 900,
        "PC0081": 1000,
        "PC0067": 900
    },
    "2022-09-28 00:00:00.0": {
        "PC0065": 826,
        "PC0081": 920,
        "PC0084": 273,
        "PC0067": 900,
        "PC0073": 80
    },
    "2022-09-29 00:00:00.0": {
        "PC0065": 900,
        "PC0067": 900,
        "PC0073": 1000
    },
    "2022-09-30 00:00:00.0": {
        "PC0073": 1000,
        "PC0067": 900
    }
}